gens/__init__.py
gens/main.py
gens-0.1.dist-info/LICENSE
gens-0.1.dist-info/METADATA
gens-0.1.dist-info/WHEEL
gens-0.1.dist-info/top_level.txt
gens-0.1.dist-info/RECORD
